wsgi.py
red_plex/__init__.py
red_plex/domain/models.py
red_plex/infrastructure/cli/cli.py
red_plex/infrastructure/cli/utils.py
red_plex/infrastructure/cli/commands/bookmarks.py
red_plex/infrastructure/cli/commands/collages.py
red_plex/infrastructure/cli/commands/config.py
red_plex/infrastructure/cli/commands/db.py
red_plex/infrastructure/cli/commands/extras.py
red_plex/infrastructure/cli/commands/gui.py
red_plex/infrastructure/config/config.py
red_plex/infrastructure/config/models.py
red_plex/infrastructure/constants/constants.py
red_plex/infrastructure/db/albums.py
red_plex/infrastructure/db/base.py
red_plex/infrastructure/db/collection.py
red_plex/infrastructure/db/local_database.py
red_plex/infrastructure/db/remote_mappings.py
red_plex/infrastructure/db/utils/csv_to_db_migrator.py
red_plex/infrastructure/gui/app.py
red_plex/infrastructure/gui/routes/bookmarks.py
red_plex/infrastructure/gui/routes/collages.py
red_plex/infrastructure/gui/routes/config.py
red_plex/infrastructure/gui/routes/database.py
red_plex/infrastructure/gui/routes/remote_mappings.py
red_plex/infrastructure/gui/routes/site_tags.py
red_plex/infrastructure/gui/routes/utils.py
red_plex/infrastructure/gui/templates/base.html
red_plex/infrastructure/gui/templates/bookmarks.html
red_plex/infrastructure/gui/templates/bookmarks_convert.html
red_plex/infrastructure/gui/templates/collages.html
red_plex/infrastructure/gui/templates/collages_convert.html
red_plex/infrastructure/gui/templates/collages_upstream_sync.html
red_plex/infrastructure/gui/templates/config.html
red_plex/infrastructure/gui/templates/config_edit.html
red_plex/infrastructure/gui/templates/database.html
red_plex/infrastructure/gui/templates/index.html
red_plex/infrastructure/gui/templates/remote_mappings.html
red_plex/infrastructure/gui/templates/remote_mappings_scan.html
red_plex/infrastructure/gui/templates/site_tags.html
red_plex/infrastructure/gui/templates/site_tags_convert.html
red_plex/infrastructure/logger/logger.py
red_plex-1.13.0.dist-info/licenses/LICENSE
red_plex-1.13.0.dist-info/METADATA
red_plex-1.13.0.dist-info/WHEEL
red_plex-1.13.0.dist-info/entry_points.txt
red_plex-1.13.0.dist-info/top_level.txt
red_plex-1.13.0.dist-info/RECORD
