Metadata-Version: 2.4
Name: red_plex
Version: 1.13.0
Summary: A CLI and web GUI tool for creating Plex collections from RED and OPS collages and bookmarks
Home-page: https://github.com/marceljungle/red-plex
Author: marceljungle
Author-email: gigi.dan2011@gmail.com
Project-URL: Bug Reports, https://github.com/marceljungle/red-plex/issues
Project-URL: Source, https://github.com/marceljungle/red-plex
Project-URL: Documentation, https://github.com/marceljungle/red-plex#readme
Keywords: plex music collections red ops redacted orpheus gazelle tracker
Classifier: Development Status :: 4 - Beta
Classifier: Intended Audience :: End Users/Desktop
Classifier: License :: OSI Approved :: MIT License
Classifier: Programming Language :: Python :: 3
Classifier: Programming Language :: Python :: 3.8
Classifier: Programming Language :: Python :: 3.9
Classifier: Programming Language :: Python :: 3.10
Classifier: Programming Language :: Python :: 3.11
Classifier: Programming Language :: Python :: 3.12
Classifier: Operating System :: OS Independent
Classifier: Topic :: Multimedia :: Sound/Audio
Classifier: Topic :: Internet :: WWW/HTTP :: Indexing/Search
Classifier: Environment :: Console
Requires-Python: >=3.8
License-File: LICENSE
Requires-Dist: plexapi
Requires-Dist: requests
Requires-Dist: tenacity
Requires-Dist: pyrate-limiter
Requires-Dist: click
Requires-Dist: pyyaml
Requires-Dist: flask
Requires-Dist: flask-socketio
Requires-Dist: gunicorn
Requires-Dist: eventlet
Requires-Dist: thefuzz[speedup]
Dynamic: author
Dynamic: author-email
Dynamic: classifier
Dynamic: description
Dynamic: description-content-type
Dynamic: home-page
Dynamic: keywords
Dynamic: license-file
Dynamic: project-url
Dynamic: requires-dist
Dynamic: requires-python
Dynamic: summary
